{
    "key": "group_service_hero",
    "title": "Услуга: поля героя",
    "fields": [
        {
            "key": "field_service_badge",
            "label": "Бейдж",
            "name": "service_badge",
            "aria-label": "",
            "type": "text",
            "instructions": "",
            "required": 0,
            "conditional_logic": false,
            "wrapper": {
                "width": "",
                "class": "",
                "id": ""
            },
            "default_value": "УСЛУГИ",
            "maxlength": "",
            "placeholder": "",
            "prepend": "",
            "append": ""
        },
        {
            "key": "field_service_desc",
            "label": "Описание",
            "name": "service_desc",
            "aria-label": "",
            "type": "textarea",
            "instructions": "",
            "required": 0,
            "conditional_logic": false,
            "wrapper": {
                "width": "",
                "class": "",
                "id": ""
            },
            "default_value": "",
            "new_lines": "",
            "maxlength": "",
            "placeholder": "",
            "rows": ""
        },
        {
            "key": "field_service_btn_text",
            "label": "Текст кнопки",
            "name": "service_btn_text",
            "aria-label": "",
            "type": "text",
            "instructions": "",
            "required": 0,
            "conditional_logic": false,
            "wrapper": {
                "width": "",
                "class": "",
                "id": ""
            },
            "default_value": "",
            "maxlength": "",
            "placeholder": "",
            "prepend": "",
            "append": ""
        },
        {
            "key": "field_service_tags",
            "label": "Теги",
            "name": "service_tags",
            "aria-label": "",
            "type": "repeater",
            "instructions": "Маленькие пилюли под описанием",
            "required": 0,
            "conditional_logic": false,
            "wrapper": {
                "width": "",
                "class": "",
                "id": ""
            },
            "layout": "table",
            "button_label": "Добавить тег",
            "min": 0,
            "max": 6,
            "rows_per_page": 20,
            "collapsed": "",
            "sub_fields": [
                {
                    "key": "field_service_tag_text",
                    "label": "Тег",
                    "name": "service_tag_text",
                    "aria-label": "",
                    "type": "text",
                    "instructions": "",
                    "required": false,
                    "conditional_logic": false,
                    "wrapper": {
                        "width": "100",
                        "class": "",
                        "id": ""
                    },
                    "default_value": "",
                    "placeholder": "кредиты",
                    "parent_repeater": "field_service_tags",
                    "maxlength": "",
                    "prepend": "",
                    "append": ""
                }
            ]
        },
        {
            "key": "field_service_hero_image",
            "label": "Фото героя",
            "name": "service_hero_image",
            "aria-label": "",
            "type": "image",
            "instructions": "",
            "required": 0,
            "conditional_logic": false,
            "wrapper": {
                "width": "",
                "class": "",
                "id": ""
            },
            "return_format": "array",
            "preview_size": "medium",
            "library": "all",
            "min_width": 0,
            "min_height": 0,
            "min_size": 0,
            "max_width": 0,
            "max_height": 0,
            "max_size": 0,
            "mime_types": ""
        }
    ],
    "location": [
        [
            {
                "param": "post_type",
                "operator": "==",
                "value": "service"
            }
        ]
    ],
    "menu_order": 0,
    "position": "normal",
    "style": "default",
    "label_placement": "top",
    "instruction_placement": "label",
    "hide_on_screen": "",
    "active": true,
    "description": "",
    "show_in_rest": false,
    "display_title": "",
    "modified": 1774248221
}
